{
  "rasa_nlu_data": {
    "common_examples": [
      {
        "intent": "greet",
        "text": "Hi"
      },
      {
        "intent": "greet",
        "text": "hey"
      },
      {
        "intent": "greet",
        "text": "heya"
      },
      {
        "intent": "greet",
        "text": "Hello"
      },
      {
        "intent": "greet",
        "text": "What's up"
      },
      {
        "intent": "greet",
        "text": "Heya"
      },
      {
        "intent": "greet",
        "text": "Greetings"
      },
      {
        "intent": "greet",
        "text": "Good  morning"
      },
      {
        "intent": "greet",
        "text": "Good afternoon"
      },
      {
        "intent": "greet",
        "text": "Good evening"
      },
      {
        "intent": "greet",
        "text": "Hey sir"
      },
      {
        "intent": "greet",
        "text": "Hi person"
      },
      {
        "intent": "greet",
        "text": "Hey robot"
      },
      {
        "intent": "greet",
        "text": "Hello bot"
      },
      {
        "intent": "goodbye",
        "text": "Bye"
      },
      {
        "intent": "goodbye",
        "text": "Goodbye"
      },
      {
        "intent": "goodbye",
        "text": "Talk to you later"
      },
      {
        "intent": "goodbye",
        "text": "See you"
      },
      {
        "intent": "goodbye",
        "text": "See you later"
      },
      {
        "intent": "goodbye",
        "text": "Bye bye"
      },
      {
        "intent": "goodbye",
        "text": "Bye for now"
      },
      {
        "intent": "goodbye",
        "text": "Goodbye bot"
      },
      {
        "intent": "affirm",
        "text": "yes"
      },
      {
        "intent": "affirm",
        "text": "yup"
      },
      {
        "intent": "affirm",
        "text": "yes, that sounds good"
      },
      {
        "intent": "affirm",
        "text": "sure"
      },
      {
        "intent": "affirm",
        "text": "definitely"
      },
      {
        "intent": "affirm",
        "text": "absolutely"
      },
      {
        "intent": "affirm",
        "text": "please do"
      },
      {
        "intent": "affirm",
        "text": "yes, please"
      },
      {
        "intent": "affirm",
        "text": "yes for sure"
      },
      {
        "intent": "thanks",
        "text": "thanks"
      },
      {
        "intent": "thanks",
        "text": "thank you"
      },
      {
        "intent": "thanks",
        "text": "Thanks a lot"
      },
      {
        "intent": "thanks",
        "text": "Thanks a bunch"
      },
      {
        "intent": "thanks",
        "text": "Thank you very much"
      },
      {
        "intent": "thanks",
        "text": "Thank you so much"
      },
      {
        "intent": "thanks+goodbye",
        "text": "Awesome. Talk to you later!"
      },
      {
        "intent": "thanks+goodbye",
        "text": "Thanks. Bye for now"
      },
      {
        "intent": "thanks+goodbye",
        "text": "Awesome, bye bye"
      },
      {
        "intent": "thanks+goodbye",
        "text": "That's great. Goodbye."
      },
      {
        "intent": "thanks+goodbye",
        "text": "Perfect. Talk to you later"
      },
      {
        "intent": "thanks+goodbye",
        "text": "Thanks! Goodbye"
      },
      {
        "intent": "thanks+goodbye",
        "text": "Th(ank you very much. Talk to you later"
      },
      {
        "intent": "thanks+goodbye",
        "text": "Thanks a lot. Bye for now"
      },
      {
        "intent": "thanks+goodbye",
        "text": "Thanks bot. Goodbye"
      },
      {
        "intent": "deny",
        "text": "No"
      },
      {
        "intent": "deny",
        "text": "Nope"
      },
      {
        "intent": "deny",
        "text": "Don't think so"
      },
      {
        "intent": "deny",
        "text": "Nooooo"
      },
      {
        "intent": "deny",
        "text": "No thanks"
      },
      {
        "intent": "deny",
        "text": "No, I don't"
      },
      {
        "intent": "inform",
        "entities": [
          {
            "start": 34,
            "end": 39,
            "value": "Tesla",
            "entity": "company"
          },
          {
            "start": 40,
            "end": 53,
            "value": "at the moment",
            "entity": "now"
          }
        ],
        "text": "I want to know the stock value of Tesla at the moment"
      },
      {
        "intent": "inform",
        "entities": [
          {
            "start": 35,
            "end": 41,
            "value": "Amazon",
            "entity": "company"
          },
          {
            "start": 42,
            "end": 55,
            "value": "at the moment",
            "entity": "now"
          }
        ],
        "text": "Can you tell me the stock price of Amazon at the moment"
      },
      {
        "intent": "inform",
        "entities": [
          {
            "start": 12,
            "end": 19,
            "value": "current",
            "entity": "now"
          },
          {
            "start": 35,
            "end": 43,
            "value": "Bilibili",
            "entity": "company"
          }
        ],
        "text": "Tell me the current stock value of Bilibili?"
      },
      {
        "intent": "inform",
        "entities": [
          {
            "start": 9,
            "end": 16,
            "value": "current",
            "entity": "now"
          },
          {
            "start": 32,
            "end": 41,
            "value": "Pinduoduo",
            "entity": "company"
          }
        ],
        "text": "Look for current stock price of Pinduoduo"
      },
      {
        "intent": "inform",
        "entities": [
          {
            "start": 21,
            "end": 27,
            "value": "Google",
            "entity": "company"
          },
          {
            "start": 28,
            "end": 37,
            "value": "right now",
            "entity": "now"
          }
        ],
        "text": "Tell me the price of Google right now"
      },
      {
        "intent": "inform",
        "entities": [
          {
            "start": 11,
            "end": 18,
            "value": "current",
            "entity": "now"
          },
          {
            "start": 34,
            "end": 43,
            "value": "Priceline",
            "entity": "company"
          }
        ],
        "text": "I need the current stock value of Priceline?"
      },
      {
        "intent": "inform",
        "entities": [
          {
            "start": 12,
            "end": 19,
            "value": "current",
            "entity": "now"
          },
          {
            "start": 30,
            "end": 37,
            "value": "Alibaba",
            "entity": "company"
          }
        ],
        "text": "What is the current shares of Alibaba?"
      },
      {
        "intent": "inform",
        "entities": [
          {
            "start": 10,
            "end": 17,
            "value": "current",
            "entity": "now"
          },
          {
            "start": 34,
            "end": 41,
            "value": "Tencent",
            "entity": "company"
          }
        ],
        "text": "How's the current share prices of Tencent?"
      },
      {
        "intent": "inform",
        "entities": [
          {
            "start": 36,
            "end": 42,
            "value": "Google",
            "entity": "company"
          },
          {
            "start": 43,
            "end": 55,
            "value": "at this time",
            "entity": "now"
          }
        ],
        "text": "Can you show me the share prices of Google at this time?"
      },
      {
        "intent": "inform",
        "entities": [
          {
            "start": 38,
            "end": 44,
            "value": "Google",
            "entity": "company"
          }
        ],
        "text": "I wish to know current stock value of Google"
      },
      {
        "intent": "inform",
        "entities": [
          {
            "start": 34,
            "end": 39,
            "value": "Tesla",
            "entity": "company"
          }
        ],
        "text": "I want to know the stock value of Tesla"
      },
      {
        "intent": "inform",
        "entities": [
          {
            "start": 35,
            "end": 41,
            "value": "Amazon",
            "entity": "company"
          }
        ],
        "text": "Can you tell me the stock price of Amazon"
      },
      {
        "intent": "inform",
        "entities": [
          {
            "start": 27,
            "end": 35,
            "value": "Bilibili",
            "entity": "company"
          }
        ],
        "text": "Tell me the stock value of Bilibili?"
      },
      {
        "intent": "inform",
        "entities": [
          {
            "start": 24,
            "end": 33,
            "value": "Pinduoduo",
            "entity": "company"
          }
        ],
        "text": "Look for stock price of Pinduoduo"
      },
      {
        "intent": "inform",
        "entities": [
          {
            "start": 21,
            "end": 27,
            "value": "Google",
            "entity": "company"
          }
        ],
        "text": "Tell me the price of Google"
      },
      {
        "intent": "inform",
        "entities": [
          {
            "start": 26,
            "end": 35,
            "value": "Priceline",
            "entity": "company"
          }
        ],
        "text": "I need the stock value of Priceline?"
      },
      {
        "intent": "inform",
        "entities": [
          {
            "start": 22,
            "end": 29,
            "value": "Alibaba",
            "entity": "company"
          }
        ],
        "text": "What is the shares of Alibaba?"
      },
      {
        "intent": "inform",
        "entities": [
          {
            "start": 26,
            "end": 33,
            "value": "Tencent",
            "entity": "company"
          }
        ],
        "text": "How's the share prices of Tencent?"
      },
      {
        "intent": "inform",
        "entities": [
          {
            "start": 36,
            "end": 42,
            "value": "Google",
            "entity": "company"
          }
        ],
        "text": "Can you show me the share prices of Google?"
      },
      {
        "intent": "inform",
        "entities": [
          {
            "start": 30,
            "end": 36,
            "value": "Google",
            "entity": "company"
          }
        ],
        "text": "I wish to know stock value of Google"
      },
      {
        "intent": "inform",
        "entities": [
          {
            "start": 0,
            "end": 9,
            "value": "right now",
            "entity": "now"
          }
        ],
        "text": "right now"
      },
      {
        "intent": "inform",
        "entities": [
          {
            "start": 0,
            "end": 12,
            "value": "at this time",
            "entity": "now"
          }
        ],
        "text": "at this time"
      },
      {
        "intent": "inform",
        "entities": [
          {
            "start": 0,
            "end": 14,
            "value": "at this moment",
            "entity": "now"
          }
        ],
        "text": "at this moment"
      },
      {
        "intent": "inform",
        "entities": [
          {
            "start": 3,
            "end": 11,
            "value": "2018.2.1",
            "entity": "time"
          }
        ],
        "text": "on 2018.2.1"
      },
      {
        "intent": "inform",
        "entities": [
          {
            "start": 3,
            "end": 11,
            "value": "2017.5.3",
            "entity": "time"
          }
        ],
        "text": "on 2017.5.3"
      },
      {
        "intent": "inform",
        "entities": [
          {
            "start": 3,
            "end": 11,
            "value": "2018.7.2",
            "entity": "time"
          }
        ],
        "text": "in 2018.7.2"
      },
      {
        "intent": "inform",
        "entities": [
          {
            "start": 3,
            "end": 12,
            "value": "2017.5.19",
            "entity": "time"
          }
        ],
        "text": "in 2017.5.19"
      },
      {
        "intent": "ask_open",
        "text": "the opening price"
      },
      {
        "intent": "ask_open",
        "text": "at the opening"
      },
      {
        "intent": "ask_open",
        "entities": [
          {
            "start": 29,
            "end": 35,
            "value": "Amazon",
            "entity": "company"
          }
        ],
        "text": "Tell me the opening price of Amazon"
      },
      {
        "intent": "ask_open",
        "entities": [
          {
            "start": 29,
            "end": 38,
            "value": "Pinduoduo",
            "entity": "company"
          },
          {
            "start": 42,
            "end": 51,
            "value": "2018.5.20",
            "entity": "time"
          }
        ],
        "text": "Show me the opening price of Pinduoduo on 2018.5.20"
      },
      {
        "intent": "ask_close",
        "text": "the closing price"
      },
      {
        "intent": "ask_close",
        "text": "at the close"
      },
      {
        "intent": "ask_close",
        "entities": [
          {
            "start": 29,
            "end": 34,
            "value": "Baidu",
            "entity": "company"
          }
        ],
        "text": "Tell me the closing price of Baidu"
      },
      {
        "intent": "ask_close",
        "entities": [
          {
            "start": 29,
            "end": 36,
            "value": "Walmart",
            "entity": "company"
          },
          {
            "start": 40,
            "end": 48,
            "value": "2017.5.2",
            "entity": "time"
          }
        ],
        "text": "Show me the closing price of Walmart on 2017.5.2"
      },
      {
        "intent": "ask_volume",
        "text": "the volume"
      },
      {
        "intent": "ask_volume",
        "text": "the trading volume"
      },
      {
        "intent": "ask_volume",
        "text": "Tell me the transaction volume"
      },
      {
        "intent": "ask_volume",
        "entities": [
          {
            "start": 34,
            "end": 42,
            "value": "Bilibili",
            "entity": "company"
          }
        ],
        "text": "Show me the transaction volume of Bilibili"
      },
      {
        "intent": "ask_volume",
        "entities": [
          {
            "start": 42,
            "end": 48,
            "value": "Target",
            "entity": "company"
          },
          {
            "start": 52,
            "end": 61,
            "value": "2017.10.2",
            "entity": "time"
          }
        ],
        "text": "Can you tell me the transaction volume of Target on 2017.10.2?"
      },
      {
        "intent": "ask_high",
        "text": "the peak value"
      },
      {
        "intent": "ask_high",
        "text": "the high point"
      },
      {
        "intent": "ask_high",
        "text": "Tell me the trasaction volume"
      },
      {
        "intent": "ask_high",
        "entities": [
          {
            "start": 26,
            "end": 33,
            "value": "Tencent",
            "entity": "company"
          }
        ],
        "text": "show me the peak value of Tencent"
      },
      {
        "intent": "ask_high",
        "entities": [
          {
            "start": 42,
            "end": 50,
            "value": "Blizzard",
            "entity": "company"
          },
          {
            "start": 54,
            "end": 63,
            "value": "2017.11.2",
            "entity": "time"
          }
        ],
        "text": "Can you tell me the transaction volume of Blizzard on 2017.11.2?"
      },
      {
        "intent": "ask_historical_plot",
        "entities": [
          {
            "start": 31,
            "end": 39,
            "value": "Facebook",
            "entity": "company"
          },
          {
            "start": 45,
            "end": 53,
            "value": "2018.2.9",
            "entity": "start_time"
          },
          {
            "start": 57,
            "end": 65,
            "value": "2018.7.5",
            "entity": "end_time"
          }
        ],
        "text": "show me the historical data of Facebook from 2018.2.9 to 2018.7.5"
      },
      {
        "intent": "ask_historical_plot",
        "entities": [
          {
            "start": 38,
            "end": 43,
            "value": "Apple",
            "entity": "company"
          },
          {
            "start": 49,
            "end": 57,
            "value": "2018.5.9",
            "entity": "start_time"
          },
          {
            "start": 61,
            "end": 69,
            "value": "2018.8.1",
            "entity": "end_time"
          }
        ],
        "text": "I want to know the historical data of Apple from 2018.5.9 to 2018.8.1"
      },
      {
        "intent": "ask_historical_plot",
        "entities": [
          {
            "start": 40,
            "end": 47,
            "value": "Netflix",
            "entity": "company"
          },
          {
            "start": 53,
            "end": 61,
            "value": "2018.7.3",
            "entity": "start_time"
          },
          {
            "start": 65,
            "end": 73,
            "value": "2018.8.2",
            "entity": "end_time"
          }
        ],
        "text": "Can you tell me the past information of Netflix from 2018.7.3 to 2018.8.2?"
      },
      {
        "intent": "ask_historical_plot",
        "entities": [
          {
            "start": 32,
            "end": 39,
            "value": "Siemens",
            "entity": "company"
          },
          {
            "start": 45,
            "end": 53,
            "value": "2017.8.5",
            "entity": "start_time"
          },
          {
            "start": 57,
            "end": 67,
            "value": "2017.12.21",
            "entity": "end_time"
          }
        ],
        "text": "I need the historical values of Siemens from 2017.8.5 to 2017.12.21"
      },
      {
        "intent": "ask_historical_plot",
        "entities": [
          {
            "start": 31,
            "end": 35,
            "value": "Momo",
            "entity": "company"
          },
          {
            "start": 41,
            "end": 49,
            "value": "2018.1.2",
            "entity": "start_time"
          },
          {
            "start": 53,
            "end": 61,
            "value": "2018.3.2",
            "entity": "end_time"
          }
        ],
        "text": "show me the historical plot of Momo from 2018.1.2 to 2018.3.2"
      },
      {
        "intent": "ask_historical_plot",
        "entities": [
          {
            "start": 20,
            "end": 27,
            "value": "Walmart",
            "entity": "company"
          },
          {
            "start": 33,
            "end": 41,
            "value": "2018.5.2",
            "entity": "start_time"
          },
          {
            "start": 45,
            "end": 53,
            "value": "2018.6.1",
            "entity": "end_time"
          }
        ],
        "text": "Show me the plot of Walmart from 2018.5.2 to 2018.6.1"
      },
      {
        "intent": "ask_historical_plot",
        "entities": [
          {
            "start": 28,
            "end": 34,
            "value": "Target",
            "entity": "company"
          },
          {
            "start": 40,
            "end": 48,
            "value": "2018.2.5",
            "entity": "start_time"
          },
          {
            "start": 52,
            "end": 60,
            "value": "2018.5.3",
            "entity": "time"
          }
        ],
        "text": "can you show me the plot of Target from 2018.2.5 to 2018.5.3?"
      }
    ],
    "regex_features": [],
    "entity_synonyms": []
  }
}